add_shift_multiplier/add_shift_multi_seg.v
//Description: Add and Shift Multiplier
//Multi Segment Architecture
//Active low reset
//Negedge triggered

module add_shift_multiplier(r, ready, clock, reset, a_in, b_in, start);

//input 
input clock;            //system clock
input reset;            //Active low reset
input [7:0] a_in;       //Multiplicand
input [7:0] b_in;       //Multiplier
input start;            //Signal to start operation

//output 
output [15:0] r;        //product
output ready;           //multiplier is idle

//parameters
parameter idle= 2'b00;
parameter shift= 2'b01;
parameter add = 2'b10;

//*control path*//

//state register
reg [1:0] state;
reg [1:0] state_next;

always @(negedge clock, negedge reset)
begin
    if(~reset)
        state <= idle;
    else
        state <= state_next;
end

//next state logic

always @(state, start, b, n_next, b_next)//update the sensitivity list
begin
    case (state)
    idle: begin
        if(start)
        begin
            if(b_in[0])
                state_next <= add;
            else
                state_next <= shift;
        end
    end
    add: state_next <= shift;
    shift: begin
        if(n_next)
        begin
            if(b_next[0])
                state_next <= add;
            else
                state_next <= shift;
        end
        else
            state_next <= idle;
    end
    default: state_next <= state;
    endcase
end

//output logic
assign ready = ~|state;

//*data path*//

//data register

reg [15:0] a;
reg [7:0] b;
reg [3:0] n;            //Number of bits in multiplier and multiplicand
reg [15:0] r;
reg [15:0] a_next;
reg [7:0] b_next;
reg [3:0] n_next;            //Number of bits in multiplier and multiplicand
reg [15:0] r_next;

always @(negedge clock, negedge reset)
begin
    if(~reset)
    begin
        a <= 16'h0000;
        b <= 8'h00;
        n <= 4'h8;
        r <= 16'h0000;
    end
    else
    begin
        a <= a_next;
        b <= b_next;
        n <= n_next;
        r <= r_next;
    end
end

//routing and multiplexing circuit and functional units

always @(state, start, a, b, r, n) // update the sensitivity list
begin
    case (state)
    idle:begin
        if(start)
        begin
            a_next <= a_in;
            b_next <= b_in;
            n_next <= 4'h8;
            r_next <= 16'h0000;
        end

    end
    add: begin
        a_next <=a;
        b_next <= b;
        n_next <= n;
        r_next <= r+a;
    end
    shift: begin
        a_next <= a<<1;
        b_next <= b>>1;
        n_next <= n-1;
        r_next <= r;
    end
    default: begin
        a_next <= a;
        b_next <= b;
        n_next <= n;
        r_next <= r; 
    end 
    endcase
end


endmodule

add_shift_multiplier/multiplier_tb.v
//Description: Multiplier testbench


module multiplier_tb ();

//input
reg start, reset, clk;
reg [7:0] a_in;
reg [7:0] b_in;

//output
wire [15:0] r_out;
wire ready;

//instantiating the DUT
add_shift_multiplier DUT (.start(start), .reset(reset), .clock(clk), .a_in(a_in), .b_in(b_in), .r(r_out), .ready(ready));

//generate clock
initial
    clk = 1'b0;

always 
    #10 clk = ~clk;

//initial block 1//
/*
dumpfile
dumpvar
monitor
*/
initial 
begin
    $dumpfile ("data.vcd");
    $dumpvars (0, multiplier_tb);
    $monitor("output = %h",r_out);
end

//initial block2//
/*
giving general stimulus
*/
initial
begin
    a_in = 8'h03;
    b_in = 8'h04;

    reset = 1'b0;
    start = 1'b0;

    #12
    reset = 1'b1;
    start = 1'b1;

    #20
    start = 1'b0;

    #250
    a_in = 8'h34;
    b_in = 8'h04;
    start = 1'b1;
    #30
    start = 1'b0;

end
initial
#1550 $finish;

endmodule

add_shift_multiplier/data.vcd
$date
	Sun Dec 17 12:03:53 2023
$end
$version
	Icarus Verilog
$end
$timescale
	1s
$end
$scope module multiplier_tb $end
$var wire 1 ! ready $end
$var wire 16 " r_out [15:0] $end
$var reg 8 # a_in [7:0] $end
$var reg 8 $ b_in [7:0] $end
$var reg 1 % clk $end
$var reg 1 & reset $end
$var reg 1 ' start $end
$scope module DUT $end
$var wire 8 ( a_in [7:0] $end
$var wire 8 ) b_in [7:0] $end
$var wire 1 % clock $end
$var wire 1 & reset $end
$var wire 1 ' start $end
$var wire 1 ! ready $end
$var parameter 2 * add $end
$var parameter 2 + idle $end
$var parameter 2 , shift $end
$var reg 16 - a [15:0] $end
$var reg 16 . a_next [15:0] $end
$var reg 8 / b [7:0] $end
$var reg 8 0 b_next [7:0] $end
$var reg 4 1 n [3:0] $end
$var reg 4 2 n_next [3:0] $end
$var reg 16 3 r [15:0] $end
$var reg 16 4 r_next [15:0] $end
$var reg 2 5 state [1:0] $end
$var reg 2 6 state_next [1:0] $end
$upscope $end
$upscope $end
$enddefinitions $end
$comment Show the parameter values. $end
$dumpall
b1 ,
b0 +
b10 *
$end
#0
$dumpvars
bx 6
b0 5
bx 4
b0 3
bx 2
b1000 1
bx 0
b0 /
bx .
b0 -
b100 )
b11 (
0'
0&
0%
b100 $
b11 #
b0 "
1!
$end
#10
1%
#12
b0 4
b1000 2
b100 0
b11 .
b1 6
1'
1&
#20
b111 2
b10 0
b110 .
b100 /
b11 -
0!
b1 5
0%
#30
1%
#32
0'
#40
b10 6
b110 2
b1 0
b1100 .
b111 1
b10 /
b110 -
0%
#50
1%
#60
b1100 4
b1 6
b110 1
b1 /
b1100 -
b10 5
0%
#70
1%
#80
b1 6
b101 2
b0 0
b11000 .
b1 5
b1100 "
b1100 3
0%
#90
1%
#100
b100 2
b110000 .
b101 1
b0 /
b11000 -
0%
#110
1%
#120
b11 2
b1100000 .
b100 1
b110000 -
0%
#130
1%
#140
b10 2
b11000000 .
b11 1
b1100000 -
0%
#150
1%
#160
b1 2
b110000000 .
b10 1
b11000000 -
0%
#170
1%
#180
b0 6
b0 2
b1100000000 .
b1 1
b110000000 -
0%
#190
1%
#200
1!
b0 5
b0 1
b1100000000 -
0%
#210
1%
#220
0%
#230
1%
#240
0%
#250
1%
#260
0%
#270
1%
#280
0%
#282
b0 4
b1000 2
b100 0
b110100 .
b1 6
1'
b110100 #
b110100 (
#290
1%
#300
b111 2
b10 0
b1101000 .
b0 "
b0 3
b1000 1
b100 /
b110100 -
0!
b1 5
0%
#310
1%
#312
0'
#320
b10 6
b110 2
b1 0
b11010000 .
b111 1
b10 /
b1101000 -
0%
#330
1%
#340
b11010000 4
b1 6
b110 1
b1 /
b11010000 -
b10 5
0%
#350
1%
#360
b1 6
b101 2
b0 0
b110100000 .
b1 5
b11010000 "
b11010000 3
0%
#370
1%
#380
b100 2
b1101000000 .
b101 1
b0 /
b110100000 -
0%
#390
1%
#400
b11 2
b11010000000 .
b100 1
b1101000000 -
0%
#410
1%
#420
b10 2
b110100000000 .
b11 1
b11010000000 -
0%
#430
1%
#440
b1 2
b1101000000000 .
b10 1
b110100000000 -
0%
#450
1%
#460
b0 6
b0 2
b11010000000000 .
b1 1
b1101000000000 -
0%
#470
1%
#480
1!
b0 5
b0 1
b11010000000000 -
0%
