booths_multipier/booths_multiplier.v
//Description: Booths Multiplier
//Negedge triggered
//Active low reset
//Multi segment coding style

module booths_multiplier(

//input 
input clk,              //clock
input reset,            //active low reset (use reset_n next time for active low reset)
input start,           // command to start the multiplication operation
input [7:0] a_in,       //Multiplicand/ Multiplier
input [7:0] b_in,      //Multiplicand/ Multiplier

//output
output [15:0] r_out,    //Product   
output ready        //Asserted when the multiplier is ready for new request
);
//parameters
parameter idle = 2'b00;
parameter shift = 2'b01;
parameter add = 2'b10;

//*control_path*//

//state register
reg [1:0] state;
reg [1:0] state_next;

always @ (negedge clk, negedge reset)
begin
    if(~reset)
        state<= idle;
    else    
        state <= state_next;
end


//next state logic
//data registers
reg [7:0] Q;    //Multiplicand
reg [7:0] A;    //Accumalator
reg q;          //Q[-1]    
reg [3:0] n;    //Bit width (no of iterations, need to be rechecked)
reg [7:0] Q_next;    
reg [7:0] A_next;    
reg q_next;          
reg [3:0] n_next;    
reg [7:0] M;    //Multiplier

always @(state, start, Q, Q_next, q_next, q)//update the sensitivity list
begin
    case (state)
    idle: begin
        if(start)
        begin
            if(a_in[0]^1'b0)
                state_next <= add;
            else    
                state_next <= shift;
        end
    end
    shift: begin
        if(n_next == 4'b0)
            state_next <= idle;
        else
        begin
            if(Q_next[0]^q_next)
                state_next <= add;
            else    
                state_next <= shift;
        end 
    end
    add: 
        state_next <= shift;
    default:
        state_next <= idle;
    endcase
end

//output logic
assign ready = ~|state;

//*data path*//

//data registers

always @(negedge clk, negedge reset)
begin
    if(~reset)
    begin
        Q <= 8'bx;
        A <= 8'b0;
        q <= 1'bx;
        n <= 4'd8;

        // Q <= 8'bz;
        // A <= 8'b0;
        // q <= 1'b0;
        // n <= 4'd8;

    end
    else
    begin
        Q <= Q_next;
        A <= A_next;
        q <= q_next;
        n <= n_next;
    end
end

//routing and multiplexing circuit and functional units

always @(state, start, A, Q, q, n) // update the sensitivity list
begin
    case (state)
    idle:begin
        if(start)
        begin
            Q_next <= a_in;
            M <= b_in;
            A_next <= 8'b0;
            q_next <= 1'b0;
            n_next <= 4'd8;
        end
    end
    add: begin
        if({Q[0],q} == 2'b10)
            A_next <= A-M;
        else 
            A_next <= A+M;
    end
    shift: begin
        {A_next,Q_next,q_next} <= {A[7], A, Q};
        n_next <= n -1;
    
    end
    endcase
end

//Assign Output

assign r_out = {A,Q};


endmodule

booths_multipier/booths_multiplier_tb.v
//Description: Booths Multiplier testbench


module booths_multiplier_tb ();

//input
reg start, reset, clk;
reg [7:0] a_in;
reg [7:0] b_in;

//output
wire [15:0] r_out;
wire ready;

//instantiating the DUT
booths_multiplier DUT (.start(start), .reset(reset), .clk(clk), .a_in(a_in), .b_in(b_in), .r_out(r_out), .ready(ready));

//generate clock
initial
    clk = 1'b0;

always 
    #10 clk = ~clk;

//initial block 1//
/*
dumpfile
dumpvar
monitor
*/
initial 
begin
    $dumpfile ("data.vcd");
    $dumpvars (0, booths_multiplier_tb);
    $monitor("output = %h",r_out);
end

//initial block2//
/*
giving general stimulus
*/
initial
begin
    a_in = 8'h03;
    b_in = 8'h04;

    reset = 1'b0;
    start = 1'b0;

    #12
    reset = 1'b1;
    start = 1'b1;

    #20
    start = 1'b0;

    #250
    a_in = 8'hfd;
    b_in = 8'h04;
    start = 1'b1;
    #30
    start = 1'b0;

    #250
    a_in = 8'h03;
    b_in = 8'hfc;
    start = 1'b1;
    #30
    start = 1'b0;

    #250
    a_in = 8'hfd;
    b_in = 8'hfc;
    start = 1'b1;
    #30
    start = 1'b0;

    #250
    a_in = 8'h34;
    b_in = 8'h04;
    start = 1'b1;
    #30
    start = 1'b0;

end
initial
#1550 $finish;

endmodule

booths_multiplier/data.vcd
$date
	Tue Dec 12 12:27:39 2023
$end
$version
	Icarus Verilog
$end
$timescale
	1s
$end
$scope module booths_multiplier_tb $end
$var wire 1 ! ready $end
$var wire 16 " r_out [15:0] $end
$var reg 8 # a_in [7:0] $end
$var reg 8 $ b_in [7:0] $end
$var reg 1 % clk $end
$var reg 1 & reset $end
$var reg 1 ' start $end
$scope module DUT $end
$var wire 8 ( a_in [7:0] $end
$var wire 8 ) b_in [7:0] $end
$var wire 1 % clk $end
$var wire 1 & reset $end
$var wire 1 ' start $end
$var wire 1 ! ready $end
$var wire 16 * r_out [15:0] $end
$var parameter 2 + add $end
$var parameter 2 , idle $end
$var parameter 2 - shift $end
$var reg 8 . A [7:0] $end
$var reg 8 / A_next [7:0] $end
$var reg 8 0 M [7:0] $end
$var reg 8 1 Q [7:0] $end
$var reg 8 2 Q_next [7:0] $end
$var reg 4 3 n [3:0] $end
$var reg 4 4 n_next [3:0] $end
$var reg 1 5 q $end
$var reg 1 6 q_next $end
$var reg 2 7 state [1:0] $end
$var reg 2 8 state_next [1:0] $end
$upscope $end
$upscope $end
$enddefinitions $end
$comment Show the parameter values. $end
$dumpall
b1 -
b0 ,
b10 +
$end
#0
$dumpvars
b0 8
b0 7
x6
x5
bx 4
b1000 3
bx 2
bx 1
bx 0
bx /
b0 .
b0xxxxxxxx *
b100 )
b11 (
0'
0&
0%
b100 $
b11 #
b0xxxxxxxx "
1!
$end
#10
1%
#12
b1000 4
06
b0 /
b100 0
b11 2
b10 8
1'
1&
#20
b11111100 /
b1 8
05
b11 "
b11 *
b11 1
0!
b10 7
0%
#30
1%
#32
0'
#40
b1 8
b111 4
b11111110 /
b1 2
16
b1 7
b1111110000000011 "
b1111110000000011 *
b11111100 .
0%
#50
1%
#60
b10 8
b110 4
b11111111 /
b0 2
b111 3
15
b11111110 .
b1111111000000001 "
b1111111000000001 *
b1 1
0%
#70
1%
#80
b11 /
b1 8
b10 7
b110 3
b11111111 .
b1111111100000000 "
b1111111100000000 *
b0 1
0%
#90
1%
#100
b101 4
b1 /
b10000000 2
06
b1 8
b1100000000 "
b1100000000 *
b11 .
b1 7
0%
#110
1%
#120
b100 4
b0 /
b11000000 2
b101 3
05
b1 .
b110000000 "
b110000000 *
b10000000 1
0%
#130
1%
#140
b11 4
b1100000 2
b100 3
b0 .
b11000000 "
b11000000 *
b11000000 1
0%
#150
1%
#160
b10 4
b110000 2
b11 3
b1100000 "
b1100000 *
b1100000 1
0%
#170
1%
#180
b1 4
b11000 2
b10 3
b110000 "
b110000 *
b110000 1
0%
#190
1%
#200
b0 8
b0 4
b1100 2
b1 3
b11000 "
b11000 *
b11000 1
0%
#210
1%
#220
b0 3
b1100 "
b1100 *
b1100 1
1!
b0 7
0%
#230
1%
#240
0%
#250
1%
#260
0%
#270
1%
#280
0%
#282
b1000 4
b11111101 2
b10 8
1'
b11111101 #
b11111101 (
#290
1%
#300
b11111100 /
b1 8
b1000 3
b11111101 "
b11111101 *
b11111101 1
0!
b10 7
0%
#310
1%
#312
0'
#320
b10 8
b111 4
b11111110 /
b1111110 2
16
b1 7
b1111110011111101 "
b1111110011111101 *
b11111100 .
0%
#330
1%
#340
b10 /
b1 8
b111 3
15
b11111110 .
b1111111001111110 "
b1111111001111110 *
b1111110 1
b10 7
0%
#350
1%
#360
b10 8
b110 4
b1 /
b111111 2
06
b1 7
b1001111110 "
b1001111110 *
b10 .
0%
#370
1%
#380
b11111101 /
b1 8
b110 3
05
b1 .
b100111111 "
b100111111 *
b111111 1
b10 7
0%
#390
1%
#400
b1 8
b101 4
b11111110 /
b10011111 2
16
b1 7
b1111110100111111 "
b1111110100111111 *
b11111101 .
0%
#410
1%
#420
b100 4
b11111111 /
b1001111 2
b101 3
15
b11111110 .
b1111111010011111 "
b1111111010011111 *
b10011111 1
0%
#430
1%
#440
b11 4
b10100111 2
b100 3
b11111111 .
b1111111101001111 "
b1111111101001111 *
b1001111 1
0%
#450
1%
#460
b10 4
b11010011 2
b11 3
b1111111110100111 "
b1111111110100111 *
b10100111 1
0%
#470
1%
#480
b1 4
b11101001 2
b10 3
b1111111111010011 "
b1111111111010011 *
b11010011 1
0%
#490
1%
#500
b0 8
b0 4
b11110100 2
b1 3
b1111111111101001 "
b1111111111101001 *
b11101001 1
0%
#510
1%
#520
1!
b0 7
b0 3
b1111111111110100 "
b1111111111110100 *
b11110100 1
0%
#530
1%
#540
0%
#550
1%
#560
0%
#562
b1000 4
06
b0 /
b11111100 0
b11 2
b10 8
1'
b11111100 $
b11111100 )
b11 #
b11 (
#570
1%
#580
b100 /
b1 8
b1000 3
05
b0 .
b11 "
b11 *
b11 1
0!
b10 7
0%
#590
1%
#592
0'
#600
b1 8
b111 4
b10 /
b1 2
16
b1 7
b10000000011 "
b10000000011 *
b100 .
0%
#610
1%
#620
b10 8
b110 4
b1 /
b0 2
b111 3
15
b10 .
b1000000001 "
b1000000001 *
b1 1
0%
#630
1%
#640
b11111101 /
b1 8
b10 7
b110 3
b1 .
b100000000 "
b100000000 *
b0 1
0%
#650
1%
#660
b101 4
b11111110 /
b10000000 2
06
b1 8
b1111110100000000 "
b1111110100000000 *
b11111101 .
b1 7
0%
#670
1%
#680
b100 4
b11111111 /
b1000000 2
b101 3
05
b11111110 .
b1111111010000000 "
b1111111010000000 *
b10000000 1
0%
#690
1%
#700
b11 4
b10100000 2
b100 3
b11111111 .
b1111111101000000 "
b1111111101000000 *
b1000000 1
0%
#710
1%
#720
b10 4
b11010000 2
b11 3
b1111111110100000 "
b1111111110100000 *
b10100000 1
0%
#730
1%
#740
b1 4
b11101000 2
b10 3
b1111111111010000 "
b1111111111010000 *
b11010000 1
0%
#750
1%
#760
b0 8
b0 4
b11110100 2
b1 3
b1111111111101000 "
b1111111111101000 *
b11101000 1
0%
#770
1%
#780
b0 3
b1111111111110100 "
b1111111111110100 *
b11110100 1
1!
b0 7
0%
#790
1%
#800
0%
#810
1%
#820
0%
#830
1%
#840
0%
#842
b1000 4
b0 /
b11111101 2
b10 8
1'
b11111101 #
b11111101 (
#850
1%
#860
b100 /
b1 8
b1000 3
b0 .
b11111101 "
b11111101 *
b11111101 1
0!
b10 7
0%
#870
1%
#872
0'
#880
b10 8
b111 4
b10 /
b1111110 2
16
b1 7
b10011111101 "
b10011111101 *
b100 .
0%
#890
1%
#900
b11111110 /
b1 8
b111 3
15
b10 .
b1001111110 "
b1001111110 *
b1111110 1
b10 7
0%
#910
1%
#920
b10 8
b110 4
b11111111 /
b111111 2
06
b1 7
b1111111001111110 "
b1111111001111110 *
b11111110 .
0%
#930
1%
#940
b11 /
b1 8
b110 3
05
b11111111 .
b1111111100111111 "
b1111111100111111 *
b111111 1
b10 7
0%
#950
1%
#960
b1 8
b101 4
b1 /
b10011111 2
16
b1 7
b1100111111 "
b1100111111 *
b11 .
0%
#970
1%
#980
b100 4
b0 /
b11001111 2
b101 3
15
b1 .
b110011111 "
b110011111 *
b10011111 1
0%
#990
1%
#1000
b11 4
b1100111 2
b100 3
b0 .
b11001111 "
b11001111 *
b11001111 1
0%
#1010
1%
#1020
b10 4
b110011 2
b11 3
b1100111 "
b1100111 *
b1100111 1
0%
#1030
1%
#1040
b1 4
b11001 2
b10 3
b110011 "
b110011 *
b110011 1
0%
#1050
1%
#1060
b0 8
b0 4
b1100 2
b1 3
b11001 "
b11001 *
b11001 1
0%
#1070
1%
#1080
1!
b0 7
b0 3
b1100 "
b1100 *
b1100 1
0%
#1090
1%
#1100
0%
#1110
1%
#1120
0%
#1122
b1000 4
06
b100 0
b110100 2
b1 8
1'
b100 $
b100 )
b110100 #
b110100 (
#1130
1%
#1140
b111 4
b11010 2
b1000 3
05
b110100 "
b110100 *
b110100 1
0!
b1 7
0%
#1150
1%
#1152
0'
#1160
b10 8
b110 4
b1101 2
b111 3
b11010 "
b11010 *
b11010 1
0%
#1170
1%
#1180
b11111100 /
b1 8
b110 3
b1101 "
b1101 *
b1101 1
b10 7
0%
#1190
1%
#1200
b10 8
b101 4
b11111110 /
b110 2
16
b1 7
b1111110000001101 "
b1111110000001101 *
b11111100 .
0%
#1210
1%
#1220
b10 /
b1 8
b101 3
15
b11111110 .
b1111111000000110 "
b1111111000000110 *
b110 1
b10 7
0%
#1230
1%
#1240
b10 8
b100 4
b1 /
b11 2
06
b1 7
b1000000110 "
b1000000110 *
b10 .
0%
#1250
1%
#1260
b11111101 /
b1 8
b100 3
05
b1 .
b100000011 "
b100000011 *
b11 1
b10 7
0%
#1270
1%
#1280
b1 8
b11 4
b11111110 /
b10000001 2
16
b1 7
b1111110100000011 "
b1111110100000011 *
b11111101 .
0%
#1290
1%
#1300
b10 8
b10 4
b11111111 /
b1000000 2
b11 3
15
b11111110 .
b1111111010000001 "
b1111111010000001 *
b10000001 1
0%
#1310
1%
#1320
b11 /
b1 8
b10 7
b10 3
b11111111 .
b1111111101000000 "
b1111111101000000 *
b1000000 1
0%
#1330
1%
#1340
b1 4
b1 /
b10100000 2
06
b1 8
b1101000000 "
b1101000000 *
b11 .
b1 7
0%
#1350
1%
#1360
b0 8
b0 4
b0 /
b11010000 2
b1 3
05
b1 .
b110100000 "
b110100000 *
b10100000 1
0%
#1370
1%
#1380
b0 3
b0 .
b11010000 "
b11010000 *
b11010000 1
1!
b0 7
0%
