repetitive_addition_multiplier/repetitive_add_multiplier.v
//Description: Multisegment coding style, 
//active low reset,
//positive edge triggered,
//Multi segment coding style

module multiplier_repad(r, ready, clock, reset, start, a_in, b_in);
//inputs
input clock;            //system clock
input reset;            //active low reset
input start;            //command to start operation
input [7:0] a_in;       //Multiplicand/Multiplier
input [7:0] b_in;       //Multiplicand/Multiplier

//output
output ready;           //asserted when the system is idle
output [15:0] r;               //product of a_in and b_in

//states
parameter IDLE = 2'b00;
parameter AB0 = 2'b01;
parameter LOAD = 2'b10;
parameter OP = 2'b11;

//*control path*//

reg [1:0] state;
reg [1:0] state_next;

//state register
always @(posedge clock , negedge reset)//review the sensitivity list
begin
    if(~reset)
        state <= IDLE;
    else    
        state <= state_next;
end

//next state
always @(state, start, reset, n_next)//review the sensitivity list
begin
    if(~reset)
        state_next <= IDLE;
    else
    begin
        case (state)
        IDLE: begin
            if(start)
            begin
                if((~|a_in)|(~|b_in))
                    state_next <= AB0;
                else
                    state_next <= LOAD;
            end    
        end
        AB0: state_next <= IDLE;
        LOAD:state_next <= OP;
        OP: begin
            if(~|n_next)
                state_next<= IDLE;
        end
        default: state_next<= IDLE;
        endcase
    end
end

//ouput
assign ready = ~|state ;

//*data path*//

//registers

reg [7:0] a;    //a register
reg [7:0] n;    //counter
reg [15:0] r;  

reg [7:0] a_next;
reg [7:0] n_next;
reg [15:0] r_next;


always @(posedge clock,negedge reset)//review the sensitivity list
begin
    if(~reset)
    begin
        a <= 8'h00;
        n <= 8'h00;
        r <= 16'h0000;
    end
    else
    begin
        a <= a_next;
        n <= n_next;
        r <= r_next;
    end
end

//routing and multiplexing

always @(state, start,a,n,subtract_out, add_out)//review the sensitivity list
begin
    case (state)
    AB0: begin
        a_next <= a;
        n_next <= n;
        r_next <= 16'h0000;
    end
    LOAD: begin
        a_next <= a_in;
        n_next <= b_in;
        r_next <= 16'h0000;
    end
    OP: begin
        a_next <= a;
        n_next <= subtract_out;
        r_next <= add_out;
    end
    default: begin
        a_next <= a;
        n_next <= n;
        r_next <= r;
    end
    endcase

end

//functional block
wire [7:0] subtract_out;
assign subtract_out = n - 1;
wire [15:0] add_out;
assign add_out = r + {8'h00,a};

wire test;
assign test = ~|n_next;
endmodule


/*
//changes in code if we share the same adder for decrementing and addition
// one more state will be added

wire [15:0] adder_src1, adder_src2;

assign adder_src1 = ((!state[2])&(state[1])&(state[0]))? r:{8'h00,n};
assign adder_src2 = ((!state[2])&(state[1])&(state[0]))? {8'h00,a}:16'hFFFF ;
assign adder_out = adder_src1 + adder_src2;*/

repetitive_addition_multiplier/multiplier_rep_tb.v
//Description: Multiplier testbench

module multiplier_tb ();

//input
reg start, reset, clk;
reg [7:0] a_in;
reg [7:0] b_in;

//output
wire [15:0] r_out;
wire ready;

//instantiating the DUT
multiplier_repad DUT (.start(start), .reset(reset), .clock(clk), .a_in(a_in), .b_in(b_in), .r(r_out), .ready(ready));

//generate clock
initial
    clk = 1'b0;

always 
    #10 clk = ~clk;

//initial block 1//
/*
dumpfile
dumpvar
monitor
*/
initial 
begin
    $dumpfile ("data.vcd");
    $dumpvars (0, multiplier_tb);
    $monitor("output = %h",r_out);
end

//initial block2//
/*
giving general stimulus
*/
initial
begin
    a_in = 8'h03;
    b_in = 8'h04;

    reset = 1'b0;
    start = 1'b0;

    #12
    reset = 1'b1;
    start = 1'b1;

    #20
    start = 1'b0;

    #250
    a_in = 8'h34;
    b_in = 8'h04;
    start = 1'b1;
    #30
    start = 1'b0;

end
initial

endmodule

repetitive_addition_multiplier/data.vcd
$date
	Sun Dec 17 13:36:09 2023
$end
$version
	Icarus Verilog
$end
$timescale
	1s
$end
$scope module multiplier_tb $end
$var wire 1 ! ready $end
$var wire 16 " r_out [15:0] $end
$var reg 8 # a_in [7:0] $end
$var reg 8 $ b_in [7:0] $end
$var reg 1 % clk $end
$var reg 1 & reset $end
$var reg 1 ' start $end
$scope module DUT $end
$var wire 8 ( a_in [7:0] $end
$var wire 8 ) b_in [7:0] $end
$var wire 1 % clock $end
$var wire 1 & reset $end
$var wire 1 ' start $end
$var wire 1 * test $end
$var wire 8 + subtract_out [7:0] $end
$var wire 1 ! ready $end
$var wire 16 , add_out [15:0] $end
$var parameter 2 - AB0 $end
$var parameter 2 . IDLE $end
$var parameter 2 / LOAD $end
$var parameter 2 0 OP $end
$var reg 8 1 a [7:0] $end
$var reg 8 2 a_next [7:0] $end
$var reg 8 3 n [7:0] $end
$var reg 8 4 n_next [7:0] $end
$var reg 16 5 r [15:0] $end
$var reg 16 6 r_next [15:0] $end
$var reg 2 7 state [1:0] $end
$var reg 2 8 state_next [1:0] $end
$upscope $end
$upscope $end
$enddefinitions $end
$comment Show the parameter values. $end
$dumpall
b11 0
b10 /
b0 .
b1 -
$end
#0
$dumpvars
b0 8
b0 7
b0 6
b0 5
b0 4
b0 3
b0 2
b0 1
b0 ,
b11111111 +
1*
b100 )
b11 (
0'
0&
0%
b100 $
b11 #
b0 "
1!
$end
#10
1%
#12
b10 8
1'
1&
#20
0%
#30
0*
b100 4
b11 2
b11 8
0!
b10 7
1%
#32
0'
#40
0%
#50
b11 6
b11 4
b11 +
b100 3
b11 ,
b11 1
b11 7
1%
#60
0%
#70
b110 6
b10 4
b110 ,
b11 "
b11 5
b10 +
b11 3
1%
#80
0%
#90
b1001 6
b1 4
b1001 ,
b110 "
b110 5
b1 +
b10 3
1%
#100
0%
#110
b0 8
b1100 6
1*
b0 4
b1100 ,
b1001 "
b1001 5
b0 +
b1 3
1%
#120
0%
#130
b1111 ,
b1100 "
b1100 5
b11111111 +
b0 3
1!
b0 7
1%
#140
0%
#150
1%
#160
0%
#170
1%
#180
0%
#190
1%
#200
0%
#210
1%
#220
0%
#230
1%
#240
0%
#250
1%
#260
0%
#270
1%
#280
0%
#282
b10 8
1'
b110100 #
b110100 (
#290
b0 6
0*
b100 4
b110100 2
b11 8
0!
b10 7
1%
#300
0%
#310
b110100 6
b11 4
b11 7
b0 "
b0 5
b11 +
b100 3
b110100 ,
b110100 1
1%
#312
0'
#320
0%
#330
b1101000 6
b10 4
b1101000 ,
b110100 "
b110100 5
b10 +
b11 3
1%
#340
0%
#350
b10011100 6
b1 4
b10011100 ,
b1101000 "
b1101000 5
b1 +
b10 3
1%
#360
0%
#370
b0 8
b11010000 6
1*
b0 4
b11010000 ,
b10011100 "
b10011100 5
b0 +
b1 3
1%
#380
0%
#390
1!
b0 7
b100000100 ,
b11010000 "
b11010000 5
b11111111 +
b0 3
1%
